omegatau_dl/__init__.py
omegatau_dl/__main__.py
omegatau_dl/constants.py
omegatau_dl/util.py
omegatau_dl/version.py
omegatau_dl-0.0.2.dist-info/LICENSE
omegatau_dl-0.0.2.dist-info/METADATA
omegatau_dl-0.0.2.dist-info/WHEEL
omegatau_dl-0.0.2.dist-info/top_level.txt
omegatau_dl-0.0.2.dist-info/RECORD
