Metadata-Version: 2.1
Name: omegatau-dl
Version: 0.0.2
Summary: Skript to download all episodes from omegataupodcast.net
Home-page: https://gitlab.com/mjohannfunke1/omegatau-download
Author: Marcel Johannfunke
Author-email: jakunddexter@gmail.com
License: GPL3
Keywords: omegatau omegataupodcast
Platform: UNKNOWN
Classifier: Development Status :: 3 - Alpha
Classifier: License :: OSI Approved :: GNU General Public License v3 (GPLv3)
Requires-Dist: requests
